{"nodes": [{"id": "c_users_gustavo_desktop_automa_o_ifood_automa_o_apis_delivery_server_app_py", "label": "app.py", "file_type": "code", "type": "FUNCTION", "source_file": "C:\\Users\\Gustavo\\Desktop\\automa\u00e7\u00e3o ifood\\automa-o-apis-delivery\\server\\app.py", "source_location": "L1", "complexity": 1, "loc": 1}, {"id": "app_supabase_headers", "label": "_supabase_headers()", "file_type": "code", "type": "FUNCTION", "source_file": "C:\\Users\\Gustavo\\Desktop\\automa\u00e7\u00e3o ifood\\automa-o-apis-delivery\\server\\app.py", "source_location": "L76", "complexity": 1, "loc": 6}, {"id": "app_erroautenticacao", "label": "ErroAutenticacao", "file_type": "code", "type": "CLASS", "source_file": "C:\\Users\\Gustavo\\Desktop\\automa\u00e7\u00e3o ifood\\automa-o-apis-delivery\\server\\app.py", "source_location": "L84", "complexity": 1, "loc": 6}, {"id": "exception", "label": "Exception", "file_type": "code", "source_file": "", "source_location": ""}, {"id": "app_erroautenticacao_init", "label": ".__init__()", "file_type": "code", "type": "FUNCTION", "source_file": "C:\\Users\\Gustavo\\Desktop\\automa\u00e7\u00e3o ifood\\automa-o-apis-delivery\\server\\app.py", "source_location": "L87", "complexity": 1, "loc": 3}, {"id": "app_usuario_atual", "label": "usuario_atual()", "file_type": "code", "type": "FUNCTION", "source_file": "C:\\Users\\Gustavo\\Desktop\\automa\u00e7\u00e3o ifood\\automa-o-apis-delivery\\server\\app.py", "source_location": "L92", "complexity": 8, "loc": 40}, {"id": "app_requer_login", "label": "requer_login()", "file_type": "code", "type": "FUNCTION", "source_file": "C:\\Users\\Gustavo\\Desktop\\automa\u00e7\u00e3o ifood\\automa-o-apis-delivery\\server\\app.py", "source_location": "L134", "complexity": 1, "loc": 7}, {"id": "app_requer_papel", "label": "requer_papel()", "file_type": "code", "type": "FUNCTION", "source_file": "C:\\Users\\Gustavo\\Desktop\\automa\u00e7\u00e3o ifood\\automa-o-apis-delivery\\server\\app.py", "source_location": "L143", "complexity": 2, "loc": 12}, {"id": "app_merchant_id", "label": "_merchant_id()", "file_type": "code", "type": "FUNCTION", "source_file": "C:\\Users\\Gustavo\\Desktop\\automa\u00e7\u00e3o ifood\\automa-o-apis-delivery\\server\\app.py", "source_location": "L157", "complexity": 1, "loc": 3}, {"id": "app_catalog_id", "label": "_catalog_id()", "file_type": "code", "type": "FUNCTION", "source_file": "C:\\Users\\Gustavo\\Desktop\\automa\u00e7\u00e3o ifood\\automa-o-apis-delivery\\server\\app.py", "source_location": "L162", "complexity": 2, "loc": 5}, {"id": "app_categoria_id", "label": "_categoria_id()", "file_type": "code", "type": "FUNCTION", "source_file": "C:\\Users\\Gustavo\\Desktop\\automa\u00e7\u00e3o ifood\\automa-o-apis-delivery\\server\\app.py", "source_location": "L169", "complexity": 3, "loc": 6}, {"id": "app_registrar_auditoria", "label": "registrar_auditoria()", "file_type": "code", "type": "FUNCTION", "source_file": "C:\\Users\\Gustavo\\Desktop\\automa\u00e7\u00e3o ifood\\automa-o-apis-delivery\\server\\app.py", "source_location": "L177", "complexity": 3, "loc": 29}, {"id": "app_tratar_erro", "label": "tratar_erro()", "file_type": "code", "type": "FUNCTION", "source_file": "C:\\Users\\Gustavo\\Desktop\\automa\u00e7\u00e3o ifood\\automa-o-apis-delivery\\server\\app.py", "source_location": "L209", "complexity": 9, "loc": 27}, {"id": "app_saude", "label": "saude()", "file_type": "code", "type": "FUNCTION", "source_file": "C:\\Users\\Gustavo\\Desktop\\automa\u00e7\u00e3o ifood\\automa-o-apis-delivery\\server\\app.py", "source_location": "L239", "complexity": 1, "loc": 2}, {"id": "app_eu", "label": "eu()", "file_type": "code", "type": "FUNCTION", "source_file": "C:\\Users\\Gustavo\\Desktop\\automa\u00e7\u00e3o ifood\\automa-o-apis-delivery\\server\\app.py", "source_location": "L245", "complexity": 1, "loc": 4}, {"id": "app_get_lojas", "label": "get_lojas()", "file_type": "code", "type": "FUNCTION", "source_file": "C:\\Users\\Gustavo\\Desktop\\automa\u00e7\u00e3o ifood\\automa-o-apis-delivery\\server\\app.py", "source_location": "L253", "complexity": 1, "loc": 12}, {"id": "app_criar_loja", "label": "criar_loja()", "file_type": "code", "type": "FUNCTION", "source_file": "C:\\Users\\Gustavo\\Desktop\\automa\u00e7\u00e3o ifood\\automa-o-apis-delivery\\server\\app.py", "source_location": "L269", "complexity": 2, "loc": 16}, {"id": "app_remover_loja", "label": "remover_loja()", "file_type": "code", "type": "FUNCTION", "source_file": "C:\\Users\\Gustavo\\Desktop\\automa\u00e7\u00e3o ifood\\automa-o-apis-delivery\\server\\app.py", "source_location": "L289", "complexity": 1, "loc": 10}, {"id": "app_get_catalogo", "label": "get_catalogo()", "file_type": "code", "type": "FUNCTION", "source_file": "C:\\Users\\Gustavo\\Desktop\\automa\u00e7\u00e3o ifood\\automa-o-apis-delivery\\server\\app.py", "source_location": "L303", "complexity": 3, "loc": 20}, {"id": "app_criar_item", "label": "criar_item()", "file_type": "code", "type": "FUNCTION", "source_file": "C:\\Users\\Gustavo\\Desktop\\automa\u00e7\u00e3o ifood\\automa-o-apis-delivery\\server\\app.py", "source_location": "L327", "complexity": 4, "loc": 39}, {"id": "app_alterar_status", "label": "alterar_status()", "file_type": "code", "type": "FUNCTION", "source_file": "C:\\Users\\Gustavo\\Desktop\\automa\u00e7\u00e3o ifood\\automa-o-apis-delivery\\server\\app.py", "source_location": "L370", "complexity": 3, "loc": 12}, {"id": "app_alterar_preco", "label": "alterar_preco()", "file_type": "code", "type": "FUNCTION", "source_file": "C:\\Users\\Gustavo\\Desktop\\automa\u00e7\u00e3o ifood\\automa-o-apis-delivery\\server\\app.py", "source_location": "L386", "complexity": 3, "loc": 15}, {"id": "app_alterar_codigo_pdv", "label": "alterar_codigo_pdv()", "file_type": "code", "type": "FUNCTION", "source_file": "C:\\Users\\Gustavo\\Desktop\\automa\u00e7\u00e3o ifood\\automa-o-apis-delivery\\server\\app.py", "source_location": "L405", "complexity": 2, "loc": 12}, {"id": "app_pausar_em_massa", "label": "pausar_em_massa()", "file_type": "code", "type": "FUNCTION", "source_file": "C:\\Users\\Gustavo\\Desktop\\automa\u00e7\u00e3o ifood\\automa-o-apis-delivery\\server\\app.py", "source_location": "L421", "complexity": 8, "loc": 35}, {"id": "app_get_auditoria", "label": "get_auditoria()", "file_type": "code", "type": "FUNCTION", "source_file": "C:\\Users\\Gustavo\\Desktop\\automa\u00e7\u00e3o ifood\\automa-o-apis-delivery\\server\\app.py", "source_location": "L460", "complexity": 3, "loc": 30}, {"id": "app_listar_usuarios", "label": "listar_usuarios()", "file_type": "code", "type": "FUNCTION", "source_file": "C:\\Users\\Gustavo\\Desktop\\automa\u00e7\u00e3o ifood\\automa-o-apis-delivery\\server\\app.py", "source_location": "L494", "complexity": 1, "loc": 9}, {"id": "app_convidar_usuario", "label": "convidar_usuario()", "file_type": "code", "type": "FUNCTION", "source_file": "C:\\Users\\Gustavo\\Desktop\\automa\u00e7\u00e3o ifood\\automa-o-apis-delivery\\server\\app.py", "source_location": "L507", "complexity": 3, "loc": 22}, {"id": "app_resetar_senha_usuario", "label": "resetar_senha_usuario()", "file_type": "code", "type": "FUNCTION", "source_file": "C:\\Users\\Gustavo\\Desktop\\automa\u00e7\u00e3o ifood\\automa-o-apis-delivery\\server\\app.py", "source_location": "L533", "complexity": 1, "loc": 21}, {"id": "app_alterar_papel_usuario", "label": "alterar_papel_usuario()", "file_type": "code", "type": "FUNCTION", "source_file": "C:\\Users\\Gustavo\\Desktop\\automa\u00e7\u00e3o ifood\\automa-o-apis-delivery\\server\\app.py", "source_location": "L558", "complexity": 2, "loc": 16}, {"id": "app_rationale_1", "label": "API local que serve de ponte entre a interface React e a Merchant/Catalog API do", "file_type": "rationale", "source_file": "C:\\Users\\Gustavo\\Desktop\\automa\u00e7\u00e3o ifood\\automa-o-apis-delivery\\server\\app.py", "source_location": "L1"}, {"id": "app_rationale_85", "label": "Falha de login/permiss\u00e3o \u2014 sess\u00e3o ausente/expirada (401) ou papel sem acesso (40", "file_type": "rationale", "source_file": "C:\\Users\\Gustavo\\Desktop\\automa\u00e7\u00e3o ifood\\automa-o-apis-delivery\\server\\app.py", "source_location": "L85"}, {"id": "app_rationale_93", "label": "Valida a sess\u00e3o (header Authorization: Bearer <token>, emitido pelo Supabase Aut", "file_type": "rationale", "source_file": "C:\\Users\\Gustavo\\Desktop\\automa\u00e7\u00e3o ifood\\automa-o-apis-delivery\\server\\app.py", "source_location": "L93"}, {"id": "app_rationale_158", "label": "Loja alvo da requisi\u00e7\u00e3o: vem de ?loja=<id> na query string, ou a padr\u00e3o do .env.", "file_type": "rationale", "source_file": "C:\\Users\\Gustavo\\Desktop\\automa\u00e7\u00e3o ifood\\automa-o-apis-delivery\\server\\app.py", "source_location": "L158"}, {"id": "app_rationale_178", "label": "Grava uma linha na tabela `auditoria` do Supabase para toda a\u00e7\u00e3o que altera o ca", "file_type": "rationale", "source_file": "C:\\Users\\Gustavo\\Desktop\\automa\u00e7\u00e3o ifood\\automa-o-apis-delivery\\server\\app.py", "source_location": "L178"}, {"id": "app_rationale_210", "label": "Converte qualquer falha (login, rede, API do iFood/Supabase, valida\u00e7\u00e3o) numa res", "file_type": "rationale", "source_file": "C:\\Users\\Gustavo\\Desktop\\automa\u00e7\u00e3o ifood\\automa-o-apis-delivery\\server\\app.py", "source_location": "L210"}, {"id": "app_rationale_246", "label": "Devolve quem \u00e9 o usu\u00e1rio logado (id, email, nome, papel) \u2014 o front usa isso depo", "file_type": "rationale", "source_file": "C:\\Users\\Gustavo\\Desktop\\automa\u00e7\u00e3o ifood\\automa-o-apis-delivery\\server\\app.py", "source_location": "L246"}, {"id": "app_rationale_254", "label": "Lojas cadastradas em `public.lojas` no Supabase (n\u00e3o \u00e9 mais list_merchants() do", "file_type": "rationale", "source_file": "C:\\Users\\Gustavo\\Desktop\\automa\u00e7\u00e3o ifood\\automa-o-apis-delivery\\server\\app.py", "source_location": "L254"}, {"id": "app_rationale_328", "label": "Cria um item novo. S\u00f3 administrador/gerente pode \u2014 e agora isso \u00e9 checado de ver", "file_type": "rationale", "source_file": "C:\\Users\\Gustavo\\Desktop\\automa\u00e7\u00e3o ifood\\automa-o-apis-delivery\\server\\app.py", "source_location": "L328"}, {"id": "app_rationale_422", "label": "Pausa ou despausa v\u00e1rios itens de uma vez, item por item (a API do iFood n\u00e3o tem", "file_type": "rationale", "source_file": "C:\\Users\\Gustavo\\Desktop\\automa\u00e7\u00e3o ifood\\automa-o-apis-delivery\\server\\app.py", "source_location": "L422"}, {"id": "app_rationale_508", "label": "Convida algu\u00e9m por e-mail (Supabase manda o link de convite). O perfil (nome + p", "file_type": "rationale", "source_file": "C:\\Users\\Gustavo\\Desktop\\automa\u00e7\u00e3o ifood\\automa-o-apis-delivery\\server\\app.py", "source_location": "L508"}, {"id": "app_rationale_534", "label": "Define uma senha nova pra algu\u00e9m direto pela Admin API do Supabase e devolve ela", "file_type": "rationale", "source_file": "C:\\Users\\Gustavo\\Desktop\\automa\u00e7\u00e3o ifood\\automa-o-apis-delivery\\server\\app.py", "source_location": "L534"}], "edges": [{"source": "c_users_gustavo_desktop_automa_o_ifood_automa_o_apis_delivery_server_app_py", "target": "logging", "relation": "imports", "confidence": "EXTRACTED", "source_file": "C:\\Users\\Gustavo\\Desktop\\automa\u00e7\u00e3o ifood\\automa-o-apis-delivery\\server\\app.py", "source_location": "L5", "weight": 1.0}, {"source": "c_users_gustavo_desktop_automa_o_ifood_automa_o_apis_delivery_server_app_py", "target": "os", "relation": "imports", "confidence": "EXTRACTED", "source_file": "C:\\Users\\Gustavo\\Desktop\\automa\u00e7\u00e3o ifood\\automa-o-apis-delivery\\server\\app.py", "source_location": "L6", "weight": 1.0}, {"source": "c_users_gustavo_desktop_automa_o_ifood_automa_o_apis_delivery_server_app_py", "target": "secrets", "relation": "imports", "confidence": "EXTRACTED", "source_file": "C:\\Users\\Gustavo\\Desktop\\automa\u00e7\u00e3o ifood\\automa-o-apis-delivery\\server\\app.py", "source_location": "L7", "weight": 1.0}, {"source": "c_users_gustavo_desktop_automa_o_ifood_automa_o_apis_delivery_server_app_py", "target": "string", "relation": "imports", "confidence": "EXTRACTED", "source_file": "C:\\Users\\Gustavo\\Desktop\\automa\u00e7\u00e3o ifood\\automa-o-apis-delivery\\server\\app.py", "source_location": "L8", "weight": 1.0}, {"source": "c_users_gustavo_desktop_automa_o_ifood_automa_o_apis_delivery_server_app_py", "target": "sys", "relation": "imports", "confidence": "EXTRACTED", "source_file": "C:\\Users\\Gustavo\\Desktop\\automa\u00e7\u00e3o ifood\\automa-o-apis-delivery\\server\\app.py", "source_location": "L9", "weight": 1.0}, {"source": "c_users_gustavo_desktop_automa_o_ifood_automa_o_apis_delivery_server_app_py", "target": "time", "relation": "imports", "confidence": "EXTRACTED", "source_file": "C:\\Users\\Gustavo\\Desktop\\automa\u00e7\u00e3o ifood\\automa-o-apis-delivery\\server\\app.py", "source_location": "L10", "weight": 1.0}, {"source": "c_users_gustavo_desktop_automa_o_ifood_automa_o_apis_delivery_server_app_py", "target": "functools", "relation": "imports_from", "confidence": "EXTRACTED", "source_file": "C:\\Users\\Gustavo\\Desktop\\automa\u00e7\u00e3o ifood\\automa-o-apis-delivery\\server\\app.py", "source_location": "L11", "weight": 1.0}, {"source": "c_users_gustavo_desktop_automa_o_ifood_automa_o_apis_delivery_server_app_py", "target": "logging_handlers", "relation": "imports_from", "confidence": "EXTRACTED", "source_file": "C:\\Users\\Gustavo\\Desktop\\automa\u00e7\u00e3o ifood\\automa-o-apis-delivery\\server\\app.py", "source_location": "L12", "weight": 1.0}, {"source": "c_users_gustavo_desktop_automa_o_ifood_automa_o_apis_delivery_server_app_py", "target": "pathlib", "relation": "imports_from", "confidence": "EXTRACTED", "source_file": "C:\\Users\\Gustavo\\Desktop\\automa\u00e7\u00e3o ifood\\automa-o-apis-delivery\\server\\app.py", "source_location": "L13", "weight": 1.0}, {"source": "c_users_gustavo_desktop_automa_o_ifood_automa_o_apis_delivery_server_app_py", "target": "dotenv", "relation": "imports_from", "confidence": "EXTRACTED", "source_file": "C:\\Users\\Gustavo\\Desktop\\automa\u00e7\u00e3o ifood\\automa-o-apis-delivery\\server\\app.py", "source_location": "L17", "weight": 1.0}, {"source": "c_users_gustavo_desktop_automa_o_ifood_automa_o_apis_delivery_server_app_py", "target": "requests", "relation": "imports", "confidence": "EXTRACTED", "source_file": "C:\\Users\\Gustavo\\Desktop\\automa\u00e7\u00e3o ifood\\automa-o-apis-delivery\\server\\app.py", "source_location": "L21", "weight": 1.0}, {"source": "c_users_gustavo_desktop_automa_o_ifood_automa_o_apis_delivery_server_app_py", "target": "uuid", "relation": "imports", "confidence": "EXTRACTED", "source_file": "C:\\Users\\Gustavo\\Desktop\\automa\u00e7\u00e3o ifood\\automa-o-apis-delivery\\server\\app.py", "source_location": "L22", "weight": 1.0}, {"source": "c_users_gustavo_desktop_automa_o_ifood_automa_o_apis_delivery_server_app_py", "target": "flask", "relation": "imports_from", "confidence": "EXTRACTED", "source_file": "C:\\Users\\Gustavo\\Desktop\\automa\u00e7\u00e3o ifood\\automa-o-apis-delivery\\server\\app.py", "source_location": "L23", "weight": 1.0}, {"source": "c_users_gustavo_desktop_automa_o_ifood_automa_o_apis_delivery_server_app_py", "target": "flask_cors", "relation": "imports_from", "confidence": "EXTRACTED", "source_file": "C:\\Users\\Gustavo\\Desktop\\automa\u00e7\u00e3o ifood\\automa-o-apis-delivery\\server\\app.py", "source_location": "L24", "weight": 1.0}, {"source": "c_users_gustavo_desktop_automa_o_ifood_automa_o_apis_delivery_server_app_py", "target": "werkzeug_exceptions", "relation": "imports_from", "confidence": "EXTRACTED", "source_file": "C:\\Users\\Gustavo\\Desktop\\automa\u00e7\u00e3o ifood\\automa-o-apis-delivery\\server\\app.py", "source_location": "L25", "weight": 1.0}, {"source": "c_users_gustavo_desktop_automa_o_ifood_automa_o_apis_delivery_server_app_py", "target": "ifood_automacao_client", "relation": "imports_from", "confidence": "EXTRACTED", "source_file": "C:\\Users\\Gustavo\\Desktop\\automa\u00e7\u00e3o ifood\\automa-o-apis-delivery\\server\\app.py", "source_location": "L27", "weight": 1.0}, {"source": "c_users_gustavo_desktop_automa_o_ifood_automa_o_apis_delivery_server_app_py", "target": "ifood_automacao_rate_limit", "relation": "imports_from", "confidence": "EXTRACTED", "source_file": "C:\\Users\\Gustavo\\Desktop\\automa\u00e7\u00e3o ifood\\automa-o-apis-delivery\\server\\app.py", "source_location": "L36", "weight": 1.0}, {"source": "c_users_gustavo_desktop_automa_o_ifood_automa_o_apis_delivery_server_app_py", "target": "app_supabase_headers", "relation": "contains", "confidence": "EXTRACTED", "source_file": "C:\\Users\\Gustavo\\Desktop\\automa\u00e7\u00e3o ifood\\automa-o-apis-delivery\\server\\app.py", "source_location": "L76", "weight": 1.0}, {"source": "c_users_gustavo_desktop_automa_o_ifood_automa_o_apis_delivery_server_app_py", "target": "app_erroautenticacao", "relation": "contains", "confidence": "EXTRACTED", "source_file": "C:\\Users\\Gustavo\\Desktop\\automa\u00e7\u00e3o ifood\\automa-o-apis-delivery\\server\\app.py", "source_location": "L84", "weight": 1.0}, {"source": "app_erroautenticacao", "target": "exception", "relation": "inherits", "confidence": "EXTRACTED", "source_file": "C:\\Users\\Gustavo\\Desktop\\automa\u00e7\u00e3o ifood\\automa-o-apis-delivery\\server\\app.py", "source_location": "L84", "weight": 1.0}, {"source": "app_erroautenticacao", "target": "app_erroautenticacao_init", "relation": "method", "confidence": "EXTRACTED", "source_file": "C:\\Users\\Gustavo\\Desktop\\automa\u00e7\u00e3o ifood\\automa-o-apis-delivery\\server\\app.py", "source_location": "L87", "weight": 1.0}, {"source": "c_users_gustavo_desktop_automa_o_ifood_automa_o_apis_delivery_server_app_py", "target": "app_usuario_atual", "relation": "contains", "confidence": "EXTRACTED", "source_file": "C:\\Users\\Gustavo\\Desktop\\automa\u00e7\u00e3o ifood\\automa-o-apis-delivery\\server\\app.py", "source_location": "L92", "weight": 1.0}, {"source": "c_users_gustavo_desktop_automa_o_ifood_automa_o_apis_delivery_server_app_py", "target": "app_requer_login", "relation": "contains", "confidence": "EXTRACTED", "source_file": "C:\\Users\\Gustavo\\Desktop\\automa\u00e7\u00e3o ifood\\automa-o-apis-delivery\\server\\app.py", "source_location": "L134", "weight": 1.0}, {"source": "c_users_gustavo_desktop_automa_o_ifood_automa_o_apis_delivery_server_app_py", "target": "app_requer_papel", "relation": "contains", "confidence": "EXTRACTED", "source_file": "C:\\Users\\Gustavo\\Desktop\\automa\u00e7\u00e3o ifood\\automa-o-apis-delivery\\server\\app.py", "source_location": "L143", "weight": 1.0}, {"source": "c_users_gustavo_desktop_automa_o_ifood_automa_o_apis_delivery_server_app_py", "target": "app_merchant_id", "relation": "contains", "confidence": "EXTRACTED", "source_file": "C:\\Users\\Gustavo\\Desktop\\automa\u00e7\u00e3o ifood\\automa-o-apis-delivery\\server\\app.py", "source_location": "L157", "weight": 1.0}, {"source": "c_users_gustavo_desktop_automa_o_ifood_automa_o_apis_delivery_server_app_py", "target": "app_catalog_id", "relation": "contains", "confidence": "EXTRACTED", "source_file": "C:\\Users\\Gustavo\\Desktop\\automa\u00e7\u00e3o ifood\\automa-o-apis-delivery\\server\\app.py", "source_location": "L162", "weight": 1.0}, {"source": "c_users_gustavo_desktop_automa_o_ifood_automa_o_apis_delivery_server_app_py", "target": "app_categoria_id", "relation": "contains", "confidence": "EXTRACTED", "source_file": "C:\\Users\\Gustavo\\Desktop\\automa\u00e7\u00e3o ifood\\automa-o-apis-delivery\\server\\app.py", "source_location": "L169", "weight": 1.0}, {"source": "c_users_gustavo_desktop_automa_o_ifood_automa_o_apis_delivery_server_app_py", "target": "app_registrar_auditoria", "relation": "contains", "confidence": "EXTRACTED", "source_file": "C:\\Users\\Gustavo\\Desktop\\automa\u00e7\u00e3o ifood\\automa-o-apis-delivery\\server\\app.py", "source_location": "L177", "weight": 1.0}, {"source": "c_users_gustavo_desktop_automa_o_ifood_automa_o_apis_delivery_server_app_py", "target": "app_tratar_erro", "relation": "contains", "confidence": "EXTRACTED", "source_file": "C:\\Users\\Gustavo\\Desktop\\automa\u00e7\u00e3o ifood\\automa-o-apis-delivery\\server\\app.py", "source_location": "L209", "weight": 1.0}, {"source": "c_users_gustavo_desktop_automa_o_ifood_automa_o_apis_delivery_server_app_py", "target": "app_saude", "relation": "contains", "confidence": "EXTRACTED", "source_file": "C:\\Users\\Gustavo\\Desktop\\automa\u00e7\u00e3o ifood\\automa-o-apis-delivery\\server\\app.py", "source_location": "L239", "weight": 1.0}, {"source": "c_users_gustavo_desktop_automa_o_ifood_automa_o_apis_delivery_server_app_py", "target": "app_eu", "relation": "contains", "confidence": "EXTRACTED", "source_file": "C:\\Users\\Gustavo\\Desktop\\automa\u00e7\u00e3o ifood\\automa-o-apis-delivery\\server\\app.py", "source_location": "L245", "weight": 1.0}, {"source": "c_users_gustavo_desktop_automa_o_ifood_automa_o_apis_delivery_server_app_py", "target": "app_get_lojas", "relation": "contains", "confidence": "EXTRACTED", "source_file": "C:\\Users\\Gustavo\\Desktop\\automa\u00e7\u00e3o ifood\\automa-o-apis-delivery\\server\\app.py", "source_location": "L253", "weight": 1.0}, {"source": "c_users_gustavo_desktop_automa_o_ifood_automa_o_apis_delivery_server_app_py", "target": "app_criar_loja", "relation": "contains", "confidence": "EXTRACTED", "source_file": "C:\\Users\\Gustavo\\Desktop\\automa\u00e7\u00e3o ifood\\automa-o-apis-delivery\\server\\app.py", "source_location": "L269", "weight": 1.0}, {"source": "c_users_gustavo_desktop_automa_o_ifood_automa_o_apis_delivery_server_app_py", "target": "app_remover_loja", "relation": "contains", "confidence": "EXTRACTED", "source_file": "C:\\Users\\Gustavo\\Desktop\\automa\u00e7\u00e3o ifood\\automa-o-apis-delivery\\server\\app.py", "source_location": "L289", "weight": 1.0}, {"source": "c_users_gustavo_desktop_automa_o_ifood_automa_o_apis_delivery_server_app_py", "target": "app_get_catalogo", "relation": "contains", "confidence": "EXTRACTED", "source_file": "C:\\Users\\Gustavo\\Desktop\\automa\u00e7\u00e3o ifood\\automa-o-apis-delivery\\server\\app.py", "source_location": "L303", "weight": 1.0}, {"source": "c_users_gustavo_desktop_automa_o_ifood_automa_o_apis_delivery_server_app_py", "target": "app_criar_item", "relation": "contains", "confidence": "EXTRACTED", "source_file": "C:\\Users\\Gustavo\\Desktop\\automa\u00e7\u00e3o ifood\\automa-o-apis-delivery\\server\\app.py", "source_location": "L327", "weight": 1.0}, {"source": "c_users_gustavo_desktop_automa_o_ifood_automa_o_apis_delivery_server_app_py", "target": "app_alterar_status", "relation": "contains", "confidence": "EXTRACTED", "source_file": "C:\\Users\\Gustavo\\Desktop\\automa\u00e7\u00e3o ifood\\automa-o-apis-delivery\\server\\app.py", "source_location": "L370", "weight": 1.0}, {"source": "c_users_gustavo_desktop_automa_o_ifood_automa_o_apis_delivery_server_app_py", "target": "app_alterar_preco", "relation": "contains", "confidence": "EXTRACTED", "source_file": "C:\\Users\\Gustavo\\Desktop\\automa\u00e7\u00e3o ifood\\automa-o-apis-delivery\\server\\app.py", "source_location": "L386", "weight": 1.0}, {"source": "c_users_gustavo_desktop_automa_o_ifood_automa_o_apis_delivery_server_app_py", "target": "app_alterar_codigo_pdv", "relation": "contains", "confidence": "EXTRACTED", "source_file": "C:\\Users\\Gustavo\\Desktop\\automa\u00e7\u00e3o ifood\\automa-o-apis-delivery\\server\\app.py", "source_location": "L405", "weight": 1.0}, {"source": "c_users_gustavo_desktop_automa_o_ifood_automa_o_apis_delivery_server_app_py", "target": "app_pausar_em_massa", "relation": "contains", "confidence": "EXTRACTED", "source_file": "C:\\Users\\Gustavo\\Desktop\\automa\u00e7\u00e3o ifood\\automa-o-apis-delivery\\server\\app.py", "source_location": "L421", "weight": 1.0}, {"source": "c_users_gustavo_desktop_automa_o_ifood_automa_o_apis_delivery_server_app_py", "target": "app_get_auditoria", "relation": "contains", "confidence": "EXTRACTED", "source_file": "C:\\Users\\Gustavo\\Desktop\\automa\u00e7\u00e3o ifood\\automa-o-apis-delivery\\server\\app.py", "source_location": "L460", "weight": 1.0}, {"source": "c_users_gustavo_desktop_automa_o_ifood_automa_o_apis_delivery_server_app_py", "target": "app_listar_usuarios", "relation": "contains", "confidence": "EXTRACTED", "source_file": "C:\\Users\\Gustavo\\Desktop\\automa\u00e7\u00e3o ifood\\automa-o-apis-delivery\\server\\app.py", "source_location": "L494", "weight": 1.0}, {"source": "c_users_gustavo_desktop_automa_o_ifood_automa_o_apis_delivery_server_app_py", "target": "app_convidar_usuario", "relation": "contains", "confidence": "EXTRACTED", "source_file": "C:\\Users\\Gustavo\\Desktop\\automa\u00e7\u00e3o ifood\\automa-o-apis-delivery\\server\\app.py", "source_location": "L507", "weight": 1.0}, {"source": "c_users_gustavo_desktop_automa_o_ifood_automa_o_apis_delivery_server_app_py", "target": "app_resetar_senha_usuario", "relation": "contains", "confidence": "EXTRACTED", "source_file": "C:\\Users\\Gustavo\\Desktop\\automa\u00e7\u00e3o ifood\\automa-o-apis-delivery\\server\\app.py", "source_location": "L533", "weight": 1.0}, {"source": "c_users_gustavo_desktop_automa_o_ifood_automa_o_apis_delivery_server_app_py", "target": "app_alterar_papel_usuario", "relation": "contains", "confidence": "EXTRACTED", "source_file": "C:\\Users\\Gustavo\\Desktop\\automa\u00e7\u00e3o ifood\\automa-o-apis-delivery\\server\\app.py", "source_location": "L558", "weight": 1.0}, {"source": "app_usuario_atual", "target": "app_erroautenticacao", "relation": "calls", "confidence": "EXTRACTED", "source_file": "C:\\Users\\Gustavo\\Desktop\\automa\u00e7\u00e3o ifood\\automa-o-apis-delivery\\server\\app.py", "source_location": "L98", "weight": 1.0}, {"source": "app_usuario_atual", "target": "app_supabase_headers", "relation": "calls", "confidence": "EXTRACTED", "source_file": "C:\\Users\\Gustavo\\Desktop\\automa\u00e7\u00e3o ifood\\automa-o-apis-delivery\\server\\app.py", "source_location": "L120", "weight": 1.0}, {"source": "app_registrar_auditoria", "target": "app_supabase_headers", "relation": "calls", "confidence": "EXTRACTED", "source_file": "C:\\Users\\Gustavo\\Desktop\\automa\u00e7\u00e3o ifood\\automa-o-apis-delivery\\server\\app.py", "source_location": "L192", "weight": 1.0}, {"source": "app_tratar_erro", "target": "exception", "relation": "calls", "confidence": "EXTRACTED", "source_file": "C:\\Users\\Gustavo\\Desktop\\automa\u00e7\u00e3o ifood\\automa-o-apis-delivery\\server\\app.py", "source_location": "L234", "weight": 1.0}, {"source": "app_get_lojas", "target": "app_supabase_headers", "relation": "calls", "confidence": "EXTRACTED", "source_file": "C:\\Users\\Gustavo\\Desktop\\automa\u00e7\u00e3o ifood\\automa-o-apis-delivery\\server\\app.py", "source_location": "L259", "weight": 1.0}, {"source": "app_criar_loja", "target": "app_supabase_headers", "relation": "calls", "confidence": "EXTRACTED", "source_file": "C:\\Users\\Gustavo\\Desktop\\automa\u00e7\u00e3o ifood\\automa-o-apis-delivery\\server\\app.py", "source_location": "L278", "weight": 1.0}, {"source": "app_criar_loja", "target": "app_registrar_auditoria", "relation": "calls", "confidence": "EXTRACTED", "source_file": "C:\\Users\\Gustavo\\Desktop\\automa\u00e7\u00e3o ifood\\automa-o-apis-delivery\\server\\app.py", "source_location": "L283", "weight": 1.0}, {"source": "app_remover_loja", "target": "app_supabase_headers", "relation": "calls", "confidence": "EXTRACTED", "source_file": "C:\\Users\\Gustavo\\Desktop\\automa\u00e7\u00e3o ifood\\automa-o-apis-delivery\\server\\app.py", "source_location": "L292", "weight": 1.0}, {"source": "app_remover_loja", "target": "app_registrar_auditoria", "relation": "calls", "confidence": "EXTRACTED", "source_file": "C:\\Users\\Gustavo\\Desktop\\automa\u00e7\u00e3o ifood\\automa-o-apis-delivery\\server\\app.py", "source_location": "L297", "weight": 1.0}, {"source": "app_get_catalogo", "target": "app_merchant_id", "relation": "calls", "confidence": "EXTRACTED", "source_file": "C:\\Users\\Gustavo\\Desktop\\automa\u00e7\u00e3o ifood\\automa-o-apis-delivery\\server\\app.py", "source_location": "L304", "weight": 1.0}, {"source": "app_get_catalogo", "target": "app_catalog_id", "relation": "calls", "confidence": "EXTRACTED", "source_file": "C:\\Users\\Gustavo\\Desktop\\automa\u00e7\u00e3o ifood\\automa-o-apis-delivery\\server\\app.py", "source_location": "L305", "weight": 1.0}, {"source": "app_criar_item", "target": "app_merchant_id", "relation": "calls", "confidence": "EXTRACTED", "source_file": "C:\\Users\\Gustavo\\Desktop\\automa\u00e7\u00e3o ifood\\automa-o-apis-delivery\\server\\app.py", "source_location": "L344", "weight": 1.0}, {"source": "app_criar_item", "target": "app_catalog_id", "relation": "calls", "confidence": "EXTRACTED", "source_file": "C:\\Users\\Gustavo\\Desktop\\automa\u00e7\u00e3o ifood\\automa-o-apis-delivery\\server\\app.py", "source_location": "L345", "weight": 1.0}, {"source": "app_criar_item", "target": "app_categoria_id", "relation": "calls", "confidence": "EXTRACTED", "source_file": "C:\\Users\\Gustavo\\Desktop\\automa\u00e7\u00e3o ifood\\automa-o-apis-delivery\\server\\app.py", "source_location": "L347", "weight": 1.0}, {"source": "app_criar_item", "target": "app_registrar_auditoria", "relation": "calls", "confidence": "EXTRACTED", "source_file": "C:\\Users\\Gustavo\\Desktop\\automa\u00e7\u00e3o ifood\\automa-o-apis-delivery\\server\\app.py", "source_location": "L364", "weight": 1.0}, {"source": "app_alterar_status", "target": "app_merchant_id", "relation": "calls", "confidence": "EXTRACTED", "source_file": "C:\\Users\\Gustavo\\Desktop\\automa\u00e7\u00e3o ifood\\automa-o-apis-delivery\\server\\app.py", "source_location": "L378", "weight": 1.0}, {"source": "app_alterar_status", "target": "app_registrar_auditoria", "relation": "calls", "confidence": "EXTRACTED", "source_file": "C:\\Users\\Gustavo\\Desktop\\automa\u00e7\u00e3o ifood\\automa-o-apis-delivery\\server\\app.py", "source_location": "L380", "weight": 1.0}, {"source": "app_alterar_preco", "target": "app_merchant_id", "relation": "calls", "confidence": "EXTRACTED", "source_file": "C:\\Users\\Gustavo\\Desktop\\automa\u00e7\u00e3o ifood\\automa-o-apis-delivery\\server\\app.py", "source_location": "L397", "weight": 1.0}, {"source": "app_alterar_preco", "target": "app_registrar_auditoria", "relation": "calls", "confidence": "EXTRACTED", "source_file": "C:\\Users\\Gustavo\\Desktop\\automa\u00e7\u00e3o ifood\\automa-o-apis-delivery\\server\\app.py", "source_location": "L399", "weight": 1.0}, {"source": "app_alterar_codigo_pdv", "target": "app_merchant_id", "relation": "calls", "confidence": "EXTRACTED", "source_file": "C:\\Users\\Gustavo\\Desktop\\automa\u00e7\u00e3o ifood\\automa-o-apis-delivery\\server\\app.py", "source_location": "L413", "weight": 1.0}, {"source": "app_alterar_codigo_pdv", "target": "app_registrar_auditoria", "relation": "calls", "confidence": "EXTRACTED", "source_file": "C:\\Users\\Gustavo\\Desktop\\automa\u00e7\u00e3o ifood\\automa-o-apis-delivery\\server\\app.py", "source_location": "L415", "weight": 1.0}, {"source": "app_pausar_em_massa", "target": "app_merchant_id", "relation": "calls", "confidence": "EXTRACTED", "source_file": "C:\\Users\\Gustavo\\Desktop\\automa\u00e7\u00e3o ifood\\automa-o-apis-delivery\\server\\app.py", "source_location": "L435", "weight": 1.0}, {"source": "app_pausar_em_massa", "target": "app_registrar_auditoria", "relation": "calls", "confidence": "EXTRACTED", "source_file": "C:\\Users\\Gustavo\\Desktop\\automa\u00e7\u00e3o ifood\\automa-o-apis-delivery\\server\\app.py", "source_location": "L445", "weight": 1.0}, {"source": "app_get_auditoria", "target": "app_supabase_headers", "relation": "calls", "confidence": "EXTRACTED", "source_file": "C:\\Users\\Gustavo\\Desktop\\automa\u00e7\u00e3o ifood\\automa-o-apis-delivery\\server\\app.py", "source_location": "L468", "weight": 1.0}, {"source": "app_listar_usuarios", "target": "app_supabase_headers", "relation": "calls", "confidence": "EXTRACTED", "source_file": "C:\\Users\\Gustavo\\Desktop\\automa\u00e7\u00e3o ifood\\automa-o-apis-delivery\\server\\app.py", "source_location": "L497", "weight": 1.0}, {"source": "app_convidar_usuario", "target": "app_supabase_headers", "relation": "calls", "confidence": "EXTRACTED", "source_file": "C:\\Users\\Gustavo\\Desktop\\automa\u00e7\u00e3o ifood\\automa-o-apis-delivery\\server\\app.py", "source_location": "L522", "weight": 1.0}, {"source": "app_convidar_usuario", "target": "app_registrar_auditoria", "relation": "calls", "confidence": "EXTRACTED", "source_file": "C:\\Users\\Gustavo\\Desktop\\automa\u00e7\u00e3o ifood\\automa-o-apis-delivery\\server\\app.py", "source_location": "L527", "weight": 1.0}, {"source": "app_resetar_senha_usuario", "target": "app_supabase_headers", "relation": "calls", "confidence": "EXTRACTED", "source_file": "C:\\Users\\Gustavo\\Desktop\\automa\u00e7\u00e3o ifood\\automa-o-apis-delivery\\server\\app.py", "source_location": "L547", "weight": 1.0}, {"source": "app_resetar_senha_usuario", "target": "app_registrar_auditoria", "relation": "calls", "confidence": "EXTRACTED", "source_file": "C:\\Users\\Gustavo\\Desktop\\automa\u00e7\u00e3o ifood\\automa-o-apis-delivery\\server\\app.py", "source_location": "L552", "weight": 1.0}, {"source": "app_alterar_papel_usuario", "target": "app_supabase_headers", "relation": "calls", "confidence": "EXTRACTED", "source_file": "C:\\Users\\Gustavo\\Desktop\\automa\u00e7\u00e3o ifood\\automa-o-apis-delivery\\server\\app.py", "source_location": "L566", "weight": 1.0}, {"source": "app_alterar_papel_usuario", "target": "app_registrar_auditoria", "relation": "calls", "confidence": "EXTRACTED", "source_file": "C:\\Users\\Gustavo\\Desktop\\automa\u00e7\u00e3o ifood\\automa-o-apis-delivery\\server\\app.py", "source_location": "L572", "weight": 1.0}, {"source": "app_rationale_1", "target": "c_users_gustavo_desktop_automa_o_ifood_automa_o_apis_delivery_server_app_py", "relation": "rationale_for", "confidence": "EXTRACTED", "source_file": "C:\\Users\\Gustavo\\Desktop\\automa\u00e7\u00e3o ifood\\automa-o-apis-delivery\\server\\app.py", "source_location": "L1", "weight": 1.0}, {"source": "app_rationale_85", "target": "app_erroautenticacao", "relation": "rationale_for", "confidence": "EXTRACTED", "source_file": "C:\\Users\\Gustavo\\Desktop\\automa\u00e7\u00e3o ifood\\automa-o-apis-delivery\\server\\app.py", "source_location": "L85", "weight": 1.0}, {"source": "app_rationale_93", "target": "app_usuario_atual", "relation": "rationale_for", "confidence": "EXTRACTED", "source_file": "C:\\Users\\Gustavo\\Desktop\\automa\u00e7\u00e3o ifood\\automa-o-apis-delivery\\server\\app.py", "source_location": "L93", "weight": 1.0}, {"source": "app_rationale_158", "target": "app_merchant_id", "relation": "rationale_for", "confidence": "EXTRACTED", "source_file": "C:\\Users\\Gustavo\\Desktop\\automa\u00e7\u00e3o ifood\\automa-o-apis-delivery\\server\\app.py", "source_location": "L158", "weight": 1.0}, {"source": "app_rationale_178", "target": "app_registrar_auditoria", "relation": "rationale_for", "confidence": "EXTRACTED", "source_file": "C:\\Users\\Gustavo\\Desktop\\automa\u00e7\u00e3o ifood\\automa-o-apis-delivery\\server\\app.py", "source_location": "L178", "weight": 1.0}, {"source": "app_rationale_210", "target": "app_tratar_erro", "relation": "rationale_for", "confidence": "EXTRACTED", "source_file": "C:\\Users\\Gustavo\\Desktop\\automa\u00e7\u00e3o ifood\\automa-o-apis-delivery\\server\\app.py", "source_location": "L210", "weight": 1.0}, {"source": "app_rationale_246", "target": "app_eu", "relation": "rationale_for", "confidence": "EXTRACTED", "source_file": "C:\\Users\\Gustavo\\Desktop\\automa\u00e7\u00e3o ifood\\automa-o-apis-delivery\\server\\app.py", "source_location": "L246", "weight": 1.0}, {"source": "app_rationale_254", "target": "app_get_lojas", "relation": "rationale_for", "confidence": "EXTRACTED", "source_file": "C:\\Users\\Gustavo\\Desktop\\automa\u00e7\u00e3o ifood\\automa-o-apis-delivery\\server\\app.py", "source_location": "L254", "weight": 1.0}, {"source": "app_rationale_328", "target": "app_criar_item", "relation": "rationale_for", "confidence": "EXTRACTED", "source_file": "C:\\Users\\Gustavo\\Desktop\\automa\u00e7\u00e3o ifood\\automa-o-apis-delivery\\server\\app.py", "source_location": "L328", "weight": 1.0}, {"source": "app_rationale_422", "target": "app_pausar_em_massa", "relation": "rationale_for", "confidence": "EXTRACTED", "source_file": "C:\\Users\\Gustavo\\Desktop\\automa\u00e7\u00e3o ifood\\automa-o-apis-delivery\\server\\app.py", "source_location": "L422", "weight": 1.0}, {"source": "app_rationale_508", "target": "app_convidar_usuario", "relation": "rationale_for", "confidence": "EXTRACTED", "source_file": "C:\\Users\\Gustavo\\Desktop\\automa\u00e7\u00e3o ifood\\automa-o-apis-delivery\\server\\app.py", "source_location": "L508", "weight": 1.0}, {"source": "app_rationale_534", "target": "app_resetar_senha_usuario", "relation": "rationale_for", "confidence": "EXTRACTED", "source_file": "C:\\Users\\Gustavo\\Desktop\\automa\u00e7\u00e3o ifood\\automa-o-apis-delivery\\server\\app.py", "source_location": "L534", "weight": 1.0}], "raw_calls": [{"caller_nid": "app_erroautenticacao_init", "callee": "super", "source_file": "C:\\Users\\Gustavo\\Desktop\\automa\u00e7\u00e3o ifood\\automa-o-apis-delivery\\server\\app.py", "source_location": "L88"}, {"caller_nid": "app_usuario_atual", "callee": "get", "source_file": "C:\\Users\\Gustavo\\Desktop\\automa\u00e7\u00e3o ifood\\automa-o-apis-delivery\\server\\app.py", "source_location": "L100"}, {"caller_nid": "app_usuario_atual", "callee": "strip", "source_file": "C:\\Users\\Gustavo\\Desktop\\automa\u00e7\u00e3o ifood\\automa-o-apis-delivery\\server\\app.py", "source_location": "L101"}, {"caller_nid": "app_usuario_atual", "callee": "len", "source_file": "C:\\Users\\Gustavo\\Desktop\\automa\u00e7\u00e3o ifood\\automa-o-apis-delivery\\server\\app.py", "source_location": "L101"}, {"caller_nid": "app_usuario_atual", "callee": "startswith", "source_file": "C:\\Users\\Gustavo\\Desktop\\automa\u00e7\u00e3o ifood\\automa-o-apis-delivery\\server\\app.py", "source_location": "L101"}, {"caller_nid": "app_usuario_atual", "callee": "get", "source_file": "C:\\Users\\Gustavo\\Desktop\\automa\u00e7\u00e3o ifood\\automa-o-apis-delivery\\server\\app.py", "source_location": "L106"}, {"caller_nid": "app_usuario_atual", "callee": "json", "source_file": "C:\\Users\\Gustavo\\Desktop\\automa\u00e7\u00e3o ifood\\automa-o-apis-delivery\\server\\app.py", "source_location": "L115"}, {"caller_nid": "app_usuario_atual", "callee": "get", "source_file": "C:\\Users\\Gustavo\\Desktop\\automa\u00e7\u00e3o ifood\\automa-o-apis-delivery\\server\\app.py", "source_location": "L118"}, {"caller_nid": "app_usuario_atual", "callee": "get", "source_file": "C:\\Users\\Gustavo\\Desktop\\automa\u00e7\u00e3o ifood\\automa-o-apis-delivery\\server\\app.py", "source_location": "L121"}, {"caller_nid": "app_usuario_atual", "callee": "raise_for_status", "source_file": "C:\\Users\\Gustavo\\Desktop\\automa\u00e7\u00e3o ifood\\automa-o-apis-delivery\\server\\app.py", "source_location": "L124"}, {"caller_nid": "app_usuario_atual", "callee": "json", "source_file": "C:\\Users\\Gustavo\\Desktop\\automa\u00e7\u00e3o ifood\\automa-o-apis-delivery\\server\\app.py", "source_location": "L125"}, {"caller_nid": "app_requer_login", "callee": "wraps", "source_file": "C:\\Users\\Gustavo\\Desktop\\automa\u00e7\u00e3o ifood\\automa-o-apis-delivery\\server\\app.py", "source_location": "L135"}, {"caller_nid": "app_merchant_id", "callee": "get", "source_file": "C:\\Users\\Gustavo\\Desktop\\automa\u00e7\u00e3o ifood\\automa-o-apis-delivery\\server\\app.py", "source_location": "L159"}, {"caller_nid": "app_catalog_id", "callee": "com_retry", "source_file": "C:\\Users\\Gustavo\\Desktop\\automa\u00e7\u00e3o ifood\\automa-o-apis-delivery\\server\\app.py", "source_location": "L163"}, {"caller_nid": "app_catalog_id", "callee": "ValueError", "source_file": "C:\\Users\\Gustavo\\Desktop\\automa\u00e7\u00e3o ifood\\automa-o-apis-delivery\\server\\app.py", "source_location": "L165"}, {"caller_nid": "app_categoria_id", "callee": "lower", "source_file": "C:\\Users\\Gustavo\\Desktop\\automa\u00e7\u00e3o ifood\\automa-o-apis-delivery\\server\\app.py", "source_location": "L171"}, {"caller_nid": "app_categoria_id", "callee": "strip", "source_file": "C:\\Users\\Gustavo\\Desktop\\automa\u00e7\u00e3o ifood\\automa-o-apis-delivery\\server\\app.py", "source_location": "L171"}, {"caller_nid": "app_categoria_id", "callee": "lower", "source_file": "C:\\Users\\Gustavo\\Desktop\\automa\u00e7\u00e3o ifood\\automa-o-apis-delivery\\server\\app.py", "source_location": "L171"}, {"caller_nid": "app_categoria_id", "callee": "strip", "source_file": "C:\\Users\\Gustavo\\Desktop\\automa\u00e7\u00e3o ifood\\automa-o-apis-delivery\\server\\app.py", "source_location": "L171"}, {"caller_nid": "app_categoria_id", "callee": "com_retry", "source_file": "C:\\Users\\Gustavo\\Desktop\\automa\u00e7\u00e3o ifood\\automa-o-apis-delivery\\server\\app.py", "source_location": "L173"}, {"caller_nid": "app_categoria_id", "callee": "strip", "source_file": "C:\\Users\\Gustavo\\Desktop\\automa\u00e7\u00e3o ifood\\automa-o-apis-delivery\\server\\app.py", "source_location": "L173"}, {"caller_nid": "app_categoria_id", "callee": "get", "source_file": "C:\\Users\\Gustavo\\Desktop\\automa\u00e7\u00e3o ifood\\automa-o-apis-delivery\\server\\app.py", "source_location": "L174"}, {"caller_nid": "app_registrar_auditoria", "callee": "info", "source_file": "C:\\Users\\Gustavo\\Desktop\\automa\u00e7\u00e3o ifood\\automa-o-apis-delivery\\server\\app.py", "source_location": "L183"}, {"caller_nid": "app_registrar_auditoria", "callee": "warning", "source_file": "C:\\Users\\Gustavo\\Desktop\\automa\u00e7\u00e3o ifood\\automa-o-apis-delivery\\server\\app.py", "source_location": "L186"}, {"caller_nid": "app_registrar_auditoria", "callee": "post", "source_file": "C:\\Users\\Gustavo\\Desktop\\automa\u00e7\u00e3o ifood\\automa-o-apis-delivery\\server\\app.py", "source_location": "L190"}, {"caller_nid": "app_registrar_auditoria", "callee": "raise_for_status", "source_file": "C:\\Users\\Gustavo\\Desktop\\automa\u00e7\u00e3o ifood\\automa-o-apis-delivery\\server\\app.py", "source_location": "L203"}, {"caller_nid": "app_registrar_auditoria", "callee": "error", "source_file": "C:\\Users\\Gustavo\\Desktop\\automa\u00e7\u00e3o ifood\\automa-o-apis-delivery\\server\\app.py", "source_location": "L205"}, {"caller_nid": "app_tratar_erro", "callee": "isinstance", "source_file": "C:\\Users\\Gustavo\\Desktop\\automa\u00e7\u00e3o ifood\\automa-o-apis-delivery\\server\\app.py", "source_location": "L212"}, {"caller_nid": "app_tratar_erro", "callee": "isinstance", "source_file": "C:\\Users\\Gustavo\\Desktop\\automa\u00e7\u00e3o ifood\\automa-o-apis-delivery\\server\\app.py", "source_location": "L215"}, {"caller_nid": "app_tratar_erro", "callee": "warning", "source_file": "C:\\Users\\Gustavo\\Desktop\\automa\u00e7\u00e3o ifood\\automa-o-apis-delivery\\server\\app.py", "source_location": "L216"}, {"caller_nid": "app_tratar_erro", "callee": "jsonify", "source_file": "C:\\Users\\Gustavo\\Desktop\\automa\u00e7\u00e3o ifood\\automa-o-apis-delivery\\server\\app.py", "source_location": "L217"}, {"caller_nid": "app_tratar_erro", "callee": "str", "source_file": "C:\\Users\\Gustavo\\Desktop\\automa\u00e7\u00e3o ifood\\automa-o-apis-delivery\\server\\app.py", "source_location": "L217"}, {"caller_nid": "app_tratar_erro", "callee": "isinstance", "source_file": "C:\\Users\\Gustavo\\Desktop\\automa\u00e7\u00e3o ifood\\automa-o-apis-delivery\\server\\app.py", "source_location": "L219"}, {"caller_nid": "app_tratar_erro", "callee": "str", "source_file": "C:\\Users\\Gustavo\\Desktop\\automa\u00e7\u00e3o ifood\\automa-o-apis-delivery\\server\\app.py", "source_location": "L221"}, {"caller_nid": "app_tratar_erro", "callee": "error", "source_file": "C:\\Users\\Gustavo\\Desktop\\automa\u00e7\u00e3o ifood\\automa-o-apis-delivery\\server\\app.py", "source_location": "L222"}, {"caller_nid": "app_tratar_erro", "callee": "jsonify", "source_file": "C:\\Users\\Gustavo\\Desktop\\automa\u00e7\u00e3o ifood\\automa-o-apis-delivery\\server\\app.py", "source_location": "L224"}, {"caller_nid": "app_tratar_erro", "callee": "isinstance", "source_file": "C:\\Users\\Gustavo\\Desktop\\automa\u00e7\u00e3o ifood\\automa-o-apis-delivery\\server\\app.py", "source_location": "L226"}, {"caller_nid": "app_tratar_erro", "callee": "error", "source_file": "C:\\Users\\Gustavo\\Desktop\\automa\u00e7\u00e3o ifood\\automa-o-apis-delivery\\server\\app.py", "source_location": "L227"}, {"caller_nid": "app_tratar_erro", "callee": "jsonify", "source_file": "C:\\Users\\Gustavo\\Desktop\\automa\u00e7\u00e3o ifood\\automa-o-apis-delivery\\server\\app.py", "source_location": "L228"}, {"caller_nid": "app_tratar_erro", "callee": "isinstance", "source_file": "C:\\Users\\Gustavo\\Desktop\\automa\u00e7\u00e3o ifood\\automa-o-apis-delivery\\server\\app.py", "source_location": "L230"}, {"caller_nid": "app_tratar_erro", "callee": "warning", "source_file": "C:\\Users\\Gustavo\\Desktop\\automa\u00e7\u00e3o ifood\\automa-o-apis-delivery\\server\\app.py", "source_location": "L231"}, {"caller_nid": "app_tratar_erro", "callee": "jsonify", "source_file": "C:\\Users\\Gustavo\\Desktop\\automa\u00e7\u00e3o ifood\\automa-o-apis-delivery\\server\\app.py", "source_location": "L232"}, {"caller_nid": "app_tratar_erro", "callee": "str", "source_file": "C:\\Users\\Gustavo\\Desktop\\automa\u00e7\u00e3o ifood\\automa-o-apis-delivery\\server\\app.py", "source_location": "L232"}, {"caller_nid": "app_tratar_erro", "callee": "jsonify", "source_file": "C:\\Users\\Gustavo\\Desktop\\automa\u00e7\u00e3o ifood\\automa-o-apis-delivery\\server\\app.py", "source_location": "L235"}, {"caller_nid": "app_saude", "callee": "jsonify", "source_file": "C:\\Users\\Gustavo\\Desktop\\automa\u00e7\u00e3o ifood\\automa-o-apis-delivery\\server\\app.py", "source_location": "L240"}, {"caller_nid": "app_eu", "callee": "jsonify", "source_file": "C:\\Users\\Gustavo\\Desktop\\automa\u00e7\u00e3o ifood\\automa-o-apis-delivery\\server\\app.py", "source_location": "L248"}, {"caller_nid": "app_get_lojas", "callee": "get", "source_file": "C:\\Users\\Gustavo\\Desktop\\automa\u00e7\u00e3o ifood\\automa-o-apis-delivery\\server\\app.py", "source_location": "L257"}, {"caller_nid": "app_get_lojas", "callee": "raise_for_status", "source_file": "C:\\Users\\Gustavo\\Desktop\\automa\u00e7\u00e3o ifood\\automa-o-apis-delivery\\server\\app.py", "source_location": "L263"}, {"caller_nid": "app_get_lojas", "callee": "jsonify", "source_file": "C:\\Users\\Gustavo\\Desktop\\automa\u00e7\u00e3o ifood\\automa-o-apis-delivery\\server\\app.py", "source_location": "L264"}, {"caller_nid": "app_get_lojas", "callee": "json", "source_file": "C:\\Users\\Gustavo\\Desktop\\automa\u00e7\u00e3o ifood\\automa-o-apis-delivery\\server\\app.py", "source_location": "L264"}, {"caller_nid": "app_criar_loja", "callee": "get_json", "source_file": "C:\\Users\\Gustavo\\Desktop\\automa\u00e7\u00e3o ifood\\automa-o-apis-delivery\\server\\app.py", "source_location": "L270"}, {"caller_nid": "app_criar_loja", "callee": "strip", "source_file": "C:\\Users\\Gustavo\\Desktop\\automa\u00e7\u00e3o ifood\\automa-o-apis-delivery\\server\\app.py", "source_location": "L271"}, {"caller_nid": "app_criar_loja", "callee": "str", "source_file": "C:\\Users\\Gustavo\\Desktop\\automa\u00e7\u00e3o ifood\\automa-o-apis-delivery\\server\\app.py", "source_location": "L271"}, {"caller_nid": "app_criar_loja", "callee": "get", "source_file": "C:\\Users\\Gustavo\\Desktop\\automa\u00e7\u00e3o ifood\\automa-o-apis-delivery\\server\\app.py", "source_location": "L271"}, {"caller_nid": "app_criar_loja", "callee": "strip", "source_file": "C:\\Users\\Gustavo\\Desktop\\automa\u00e7\u00e3o ifood\\automa-o-apis-delivery\\server\\app.py", "source_location": "L272"}, {"caller_nid": "app_criar_loja", "callee": "str", "source_file": "C:\\Users\\Gustavo\\Desktop\\automa\u00e7\u00e3o ifood\\automa-o-apis-delivery\\server\\app.py", "source_location": "L272"}, {"caller_nid": "app_criar_loja", "callee": "get", "source_file": "C:\\Users\\Gustavo\\Desktop\\automa\u00e7\u00e3o ifood\\automa-o-apis-delivery\\server\\app.py", "source_location": "L272"}, {"caller_nid": "app_criar_loja", "callee": "ValueError", "source_file": "C:\\Users\\Gustavo\\Desktop\\automa\u00e7\u00e3o ifood\\automa-o-apis-delivery\\server\\app.py", "source_location": "L274"}, {"caller_nid": "app_criar_loja", "callee": "post", "source_file": "C:\\Users\\Gustavo\\Desktop\\automa\u00e7\u00e3o ifood\\automa-o-apis-delivery\\server\\app.py", "source_location": "L276"}, {"caller_nid": "app_criar_loja", "callee": "raise_for_status", "source_file": "C:\\Users\\Gustavo\\Desktop\\automa\u00e7\u00e3o ifood\\automa-o-apis-delivery\\server\\app.py", "source_location": "L282"}, {"caller_nid": "app_criar_loja", "callee": "jsonify", "source_file": "C:\\Users\\Gustavo\\Desktop\\automa\u00e7\u00e3o ifood\\automa-o-apis-delivery\\server\\app.py", "source_location": "L284"}, {"caller_nid": "app_criar_loja", "callee": "json", "source_file": "C:\\Users\\Gustavo\\Desktop\\automa\u00e7\u00e3o ifood\\automa-o-apis-delivery\\server\\app.py", "source_location": "L284"}, {"caller_nid": "app_remover_loja", "callee": "delete", "source_file": "C:\\Users\\Gustavo\\Desktop\\automa\u00e7\u00e3o ifood\\automa-o-apis-delivery\\server\\app.py", "source_location": "L290"}, {"caller_nid": "app_remover_loja", "callee": "raise_for_status", "source_file": "C:\\Users\\Gustavo\\Desktop\\automa\u00e7\u00e3o ifood\\automa-o-apis-delivery\\server\\app.py", "source_location": "L296"}, {"caller_nid": "app_remover_loja", "callee": "jsonify", "source_file": "C:\\Users\\Gustavo\\Desktop\\automa\u00e7\u00e3o ifood\\automa-o-apis-delivery\\server\\app.py", "source_location": "L298"}, {"caller_nid": "app_get_catalogo", "callee": "com_retry", "source_file": "C:\\Users\\Gustavo\\Desktop\\automa\u00e7\u00e3o ifood\\automa-o-apis-delivery\\server\\app.py", "source_location": "L306"}, {"caller_nid": "app_get_catalogo", "callee": "get", "source_file": "C:\\Users\\Gustavo\\Desktop\\automa\u00e7\u00e3o ifood\\automa-o-apis-delivery\\server\\app.py", "source_location": "L309"}, {"caller_nid": "app_get_catalogo", "callee": "append", "source_file": "C:\\Users\\Gustavo\\Desktop\\automa\u00e7\u00e3o ifood\\automa-o-apis-delivery\\server\\app.py", "source_location": "L310"}, {"caller_nid": "app_get_catalogo", "callee": "get", "source_file": "C:\\Users\\Gustavo\\Desktop\\automa\u00e7\u00e3o ifood\\automa-o-apis-delivery\\server\\app.py", "source_location": "L315"}, {"caller_nid": "app_get_catalogo", "callee": "get", "source_file": "C:\\Users\\Gustavo\\Desktop\\automa\u00e7\u00e3o ifood\\automa-o-apis-delivery\\server\\app.py", "source_location": "L316"}, {"caller_nid": "app_get_catalogo", "callee": "get", "source_file": "C:\\Users\\Gustavo\\Desktop\\automa\u00e7\u00e3o ifood\\automa-o-apis-delivery\\server\\app.py", "source_location": "L317"}, {"caller_nid": "app_get_catalogo", "callee": "get", "source_file": "C:\\Users\\Gustavo\\Desktop\\automa\u00e7\u00e3o ifood\\automa-o-apis-delivery\\server\\app.py", "source_location": "L317"}, {"caller_nid": "app_get_catalogo", "callee": "get", "source_file": "C:\\Users\\Gustavo\\Desktop\\automa\u00e7\u00e3o ifood\\automa-o-apis-delivery\\server\\app.py", "source_location": "L318"}, {"caller_nid": "app_get_catalogo", "callee": "sorted", "source_file": "C:\\Users\\Gustavo\\Desktop\\automa\u00e7\u00e3o ifood\\automa-o-apis-delivery\\server\\app.py", "source_location": "L321"}, {"caller_nid": "app_get_catalogo", "callee": "jsonify", "source_file": "C:\\Users\\Gustavo\\Desktop\\automa\u00e7\u00e3o ifood\\automa-o-apis-delivery\\server\\app.py", "source_location": "L322"}, {"caller_nid": "app_criar_item", "callee": "get_json", "source_file": "C:\\Users\\Gustavo\\Desktop\\automa\u00e7\u00e3o ifood\\automa-o-apis-delivery\\server\\app.py", "source_location": "L330"}, {"caller_nid": "app_criar_item", "callee": "strip", "source_file": "C:\\Users\\Gustavo\\Desktop\\automa\u00e7\u00e3o ifood\\automa-o-apis-delivery\\server\\app.py", "source_location": "L333"}, {"caller_nid": "app_criar_item", "callee": "str", "source_file": "C:\\Users\\Gustavo\\Desktop\\automa\u00e7\u00e3o ifood\\automa-o-apis-delivery\\server\\app.py", "source_location": "L333"}, {"caller_nid": "app_criar_item", "callee": "get", "source_file": "C:\\Users\\Gustavo\\Desktop\\automa\u00e7\u00e3o ifood\\automa-o-apis-delivery\\server\\app.py", "source_location": "L333"}, {"caller_nid": "app_criar_item", "callee": "jsonify", "source_file": "C:\\Users\\Gustavo\\Desktop\\automa\u00e7\u00e3o ifood\\automa-o-apis-delivery\\server\\app.py", "source_location": "L335"}, {"caller_nid": "app_criar_item", "callee": "float", "source_file": "C:\\Users\\Gustavo\\Desktop\\automa\u00e7\u00e3o ifood\\automa-o-apis-delivery\\server\\app.py", "source_location": "L338"}, {"caller_nid": "app_criar_item", "callee": "replace", "source_file": "C:\\Users\\Gustavo\\Desktop\\automa\u00e7\u00e3o ifood\\automa-o-apis-delivery\\server\\app.py", "source_location": "L338"}, {"caller_nid": "app_criar_item", "callee": "str", "source_file": "C:\\Users\\Gustavo\\Desktop\\automa\u00e7\u00e3o ifood\\automa-o-apis-delivery\\server\\app.py", "source_location": "L338"}, {"caller_nid": "app_criar_item", "callee": "jsonify", "source_file": "C:\\Users\\Gustavo\\Desktop\\automa\u00e7\u00e3o ifood\\automa-o-apis-delivery\\server\\app.py", "source_location": "L340"}, {"caller_nid": "app_criar_item", "callee": "jsonify", "source_file": "C:\\Users\\Gustavo\\Desktop\\automa\u00e7\u00e3o ifood\\automa-o-apis-delivery\\server\\app.py", "source_location": "L342"}, {"caller_nid": "app_criar_item", "callee": "com_retry", "source_file": "C:\\Users\\Gustavo\\Desktop\\automa\u00e7\u00e3o ifood\\automa-o-apis-delivery\\server\\app.py", "source_location": "L346"}, {"caller_nid": "app_criar_item", "callee": "str", "source_file": "C:\\Users\\Gustavo\\Desktop\\automa\u00e7\u00e3o ifood\\automa-o-apis-delivery\\server\\app.py", "source_location": "L349"}, {"caller_nid": "app_criar_item", "callee": "uuid4", "source_file": "C:\\Users\\Gustavo\\Desktop\\automa\u00e7\u00e3o ifood\\automa-o-apis-delivery\\server\\app.py", "source_location": "L349"}, {"caller_nid": "app_criar_item", "callee": "strip", "source_file": "C:\\Users\\Gustavo\\Desktop\\automa\u00e7\u00e3o ifood\\automa-o-apis-delivery\\server\\app.py", "source_location": "L350"}, {"caller_nid": "app_criar_item", "callee": "strip", "source_file": "C:\\Users\\Gustavo\\Desktop\\automa\u00e7\u00e3o ifood\\automa-o-apis-delivery\\server\\app.py", "source_location": "L351"}, {"caller_nid": "app_criar_item", "callee": "str", "source_file": "C:\\Users\\Gustavo\\Desktop\\automa\u00e7\u00e3o ifood\\automa-o-apis-delivery\\server\\app.py", "source_location": "L351"}, {"caller_nid": "app_criar_item", "callee": "com_retry", "source_file": "C:\\Users\\Gustavo\\Desktop\\automa\u00e7\u00e3o ifood\\automa-o-apis-delivery\\server\\app.py", "source_location": "L353"}, {"caller_nid": "app_criar_item", "callee": "str", "source_file": "C:\\Users\\Gustavo\\Desktop\\automa\u00e7\u00e3o ifood\\automa-o-apis-delivery\\server\\app.py", "source_location": "L357"}, {"caller_nid": "app_criar_item", "callee": "uuid4", "source_file": "C:\\Users\\Gustavo\\Desktop\\automa\u00e7\u00e3o ifood\\automa-o-apis-delivery\\server\\app.py", "source_location": "L357"}, {"caller_nid": "app_criar_item", "callee": "jsonify", "source_file": "C:\\Users\\Gustavo\\Desktop\\automa\u00e7\u00e3o ifood\\automa-o-apis-delivery\\server\\app.py", "source_location": "L365"}, {"caller_nid": "app_alterar_status", "callee": "get_json", "source_file": "C:\\Users\\Gustavo\\Desktop\\automa\u00e7\u00e3o ifood\\automa-o-apis-delivery\\server\\app.py", "source_location": "L371"}, {"caller_nid": "app_alterar_status", "callee": "get", "source_file": "C:\\Users\\Gustavo\\Desktop\\automa\u00e7\u00e3o ifood\\automa-o-apis-delivery\\server\\app.py", "source_location": "L372"}, {"caller_nid": "app_alterar_status", "callee": "strip", "source_file": "C:\\Users\\Gustavo\\Desktop\\automa\u00e7\u00e3o ifood\\automa-o-apis-delivery\\server\\app.py", "source_location": "L373"}, {"caller_nid": "app_alterar_status", "callee": "str", "source_file": "C:\\Users\\Gustavo\\Desktop\\automa\u00e7\u00e3o ifood\\automa-o-apis-delivery\\server\\app.py", "source_location": "L373"}, {"caller_nid": "app_alterar_status", "callee": "get", "source_file": "C:\\Users\\Gustavo\\Desktop\\automa\u00e7\u00e3o ifood\\automa-o-apis-delivery\\server\\app.py", "source_location": "L373"}, {"caller_nid": "app_alterar_status", "callee": "ValueError", "source_file": "C:\\Users\\Gustavo\\Desktop\\automa\u00e7\u00e3o ifood\\automa-o-apis-delivery\\server\\app.py", "source_location": "L376"}, {"caller_nid": "app_alterar_status", "callee": "com_retry", "source_file": "C:\\Users\\Gustavo\\Desktop\\automa\u00e7\u00e3o ifood\\automa-o-apis-delivery\\server\\app.py", "source_location": "L379"}, {"caller_nid": "app_alterar_status", "callee": "jsonify", "source_file": "C:\\Users\\Gustavo\\Desktop\\automa\u00e7\u00e3o ifood\\automa-o-apis-delivery\\server\\app.py", "source_location": "L381"}, {"caller_nid": "app_alterar_preco", "callee": "get_json", "source_file": "C:\\Users\\Gustavo\\Desktop\\automa\u00e7\u00e3o ifood\\automa-o-apis-delivery\\server\\app.py", "source_location": "L387"}, {"caller_nid": "app_alterar_preco", "callee": "strip", "source_file": "C:\\Users\\Gustavo\\Desktop\\automa\u00e7\u00e3o ifood\\automa-o-apis-delivery\\server\\app.py", "source_location": "L388"}, {"caller_nid": "app_alterar_preco", "callee": "str", "source_file": "C:\\Users\\Gustavo\\Desktop\\automa\u00e7\u00e3o ifood\\automa-o-apis-delivery\\server\\app.py", "source_location": "L388"}, {"caller_nid": "app_alterar_preco", "callee": "get", "source_file": "C:\\Users\\Gustavo\\Desktop\\automa\u00e7\u00e3o ifood\\automa-o-apis-delivery\\server\\app.py", "source_location": "L388"}, {"caller_nid": "app_alterar_preco", "callee": "float", "source_file": "C:\\Users\\Gustavo\\Desktop\\automa\u00e7\u00e3o ifood\\automa-o-apis-delivery\\server\\app.py", "source_location": "L391"}, {"caller_nid": "app_alterar_preco", "callee": "replace", "source_file": "C:\\Users\\Gustavo\\Desktop\\automa\u00e7\u00e3o ifood\\automa-o-apis-delivery\\server\\app.py", "source_location": "L391"}, {"caller_nid": "app_alterar_preco", "callee": "str", "source_file": "C:\\Users\\Gustavo\\Desktop\\automa\u00e7\u00e3o ifood\\automa-o-apis-delivery\\server\\app.py", "source_location": "L391"}, {"caller_nid": "app_alterar_preco", "callee": "get", "source_file": "C:\\Users\\Gustavo\\Desktop\\automa\u00e7\u00e3o ifood\\automa-o-apis-delivery\\server\\app.py", "source_location": "L391"}, {"caller_nid": "app_alterar_preco", "callee": "ValueError", "source_file": "C:\\Users\\Gustavo\\Desktop\\automa\u00e7\u00e3o ifood\\automa-o-apis-delivery\\server\\app.py", "source_location": "L393"}, {"caller_nid": "app_alterar_preco", "callee": "ValueError", "source_file": "C:\\Users\\Gustavo\\Desktop\\automa\u00e7\u00e3o ifood\\automa-o-apis-delivery\\server\\app.py", "source_location": "L395"}, {"caller_nid": "app_alterar_preco", "callee": "com_retry", "source_file": "C:\\Users\\Gustavo\\Desktop\\automa\u00e7\u00e3o ifood\\automa-o-apis-delivery\\server\\app.py", "source_location": "L398"}, {"caller_nid": "app_alterar_preco", "callee": "jsonify", "source_file": "C:\\Users\\Gustavo\\Desktop\\automa\u00e7\u00e3o ifood\\automa-o-apis-delivery\\server\\app.py", "source_location": "L400"}, {"caller_nid": "app_alterar_codigo_pdv", "callee": "get_json", "source_file": "C:\\Users\\Gustavo\\Desktop\\automa\u00e7\u00e3o ifood\\automa-o-apis-delivery\\server\\app.py", "source_location": "L406"}, {"caller_nid": "app_alterar_codigo_pdv", "callee": "strip", "source_file": "C:\\Users\\Gustavo\\Desktop\\automa\u00e7\u00e3o ifood\\automa-o-apis-delivery\\server\\app.py", "source_location": "L407"}, {"caller_nid": "app_alterar_codigo_pdv", "callee": "str", "source_file": "C:\\Users\\Gustavo\\Desktop\\automa\u00e7\u00e3o ifood\\automa-o-apis-delivery\\server\\app.py", "source_location": "L407"}, {"caller_nid": "app_alterar_codigo_pdv", "callee": "get", "source_file": "C:\\Users\\Gustavo\\Desktop\\automa\u00e7\u00e3o ifood\\automa-o-apis-delivery\\server\\app.py", "source_location": "L407"}, {"caller_nid": "app_alterar_codigo_pdv", "callee": "strip", "source_file": "C:\\Users\\Gustavo\\Desktop\\automa\u00e7\u00e3o ifood\\automa-o-apis-delivery\\server\\app.py", "source_location": "L409"}, {"caller_nid": "app_alterar_codigo_pdv", "callee": "str", "source_file": "C:\\Users\\Gustavo\\Desktop\\automa\u00e7\u00e3o ifood\\automa-o-apis-delivery\\server\\app.py", "source_location": "L409"}, {"caller_nid": "app_alterar_codigo_pdv", "callee": "get", "source_file": "C:\\Users\\Gustavo\\Desktop\\automa\u00e7\u00e3o ifood\\automa-o-apis-delivery\\server\\app.py", "source_location": "L409"}, {"caller_nid": "app_alterar_codigo_pdv", "callee": "ValueError", "source_file": "C:\\Users\\Gustavo\\Desktop\\automa\u00e7\u00e3o ifood\\automa-o-apis-delivery\\server\\app.py", "source_location": "L411"}, {"caller_nid": "app_alterar_codigo_pdv", "callee": "com_retry", "source_file": "C:\\Users\\Gustavo\\Desktop\\automa\u00e7\u00e3o ifood\\automa-o-apis-delivery\\server\\app.py", "source_location": "L414"}, {"caller_nid": "app_alterar_codigo_pdv", "callee": "jsonify", "source_file": "C:\\Users\\Gustavo\\Desktop\\automa\u00e7\u00e3o ifood\\automa-o-apis-delivery\\server\\app.py", "source_location": "L416"}, {"caller_nid": "app_pausar_em_massa", "callee": "get_json", "source_file": "C:\\Users\\Gustavo\\Desktop\\automa\u00e7\u00e3o ifood\\automa-o-apis-delivery\\server\\app.py", "source_location": "L425"}, {"caller_nid": "app_pausar_em_massa", "callee": "get", "source_file": "C:\\Users\\Gustavo\\Desktop\\automa\u00e7\u00e3o ifood\\automa-o-apis-delivery\\server\\app.py", "source_location": "L426"}, {"caller_nid": "app_pausar_em_massa", "callee": "get", "source_file": "C:\\Users\\Gustavo\\Desktop\\automa\u00e7\u00e3o ifood\\automa-o-apis-delivery\\server\\app.py", "source_location": "L427"}, {"caller_nid": "app_pausar_em_massa", "callee": "ValueError", "source_file": "C:\\Users\\Gustavo\\Desktop\\automa\u00e7\u00e3o ifood\\automa-o-apis-delivery\\server\\app.py", "source_location": "L431"}, {"caller_nid": "app_pausar_em_massa", "callee": "isinstance", "source_file": "C:\\Users\\Gustavo\\Desktop\\automa\u00e7\u00e3o ifood\\automa-o-apis-delivery\\server\\app.py", "source_location": "L432"}, {"caller_nid": "app_pausar_em_massa", "callee": "ValueError", "source_file": "C:\\Users\\Gustavo\\Desktop\\automa\u00e7\u00e3o ifood\\automa-o-apis-delivery\\server\\app.py", "source_location": "L433"}, {"caller_nid": "app_pausar_em_massa", "callee": "enumerate", "source_file": "C:\\Users\\Gustavo\\Desktop\\automa\u00e7\u00e3o ifood\\automa-o-apis-delivery\\server\\app.py", "source_location": "L438"}, {"caller_nid": "app_pausar_em_massa", "callee": "strip", "source_file": "C:\\Users\\Gustavo\\Desktop\\automa\u00e7\u00e3o ifood\\automa-o-apis-delivery\\server\\app.py", "source_location": "L439"}, {"caller_nid": "app_pausar_em_massa", "callee": "str", "source_file": "C:\\Users\\Gustavo\\Desktop\\automa\u00e7\u00e3o ifood\\automa-o-apis-delivery\\server\\app.py", "source_location": "L439"}, {"caller_nid": "app_pausar_em_massa", "callee": "get", "source_file": "C:\\Users\\Gustavo\\Desktop\\automa\u00e7\u00e3o ifood\\automa-o-apis-delivery\\server\\app.py", "source_location": "L439"}, {"caller_nid": "app_pausar_em_massa", "callee": "strip", "source_file": "C:\\Users\\Gustavo\\Desktop\\automa\u00e7\u00e3o ifood\\automa-o-apis-delivery\\server\\app.py", "source_location": "L440"}, {"caller_nid": "app_pausar_em_massa", "callee": "str", "source_file": "C:\\Users\\Gustavo\\Desktop\\automa\u00e7\u00e3o ifood\\automa-o-apis-delivery\\server\\app.py", "source_location": "L440"}, {"caller_nid": "app_pausar_em_massa", "callee": "get", "source_file": "C:\\Users\\Gustavo\\Desktop\\automa\u00e7\u00e3o ifood\\automa-o-apis-delivery\\server\\app.py", "source_location": "L440"}, {"caller_nid": "app_pausar_em_massa", "callee": "com_retry", "source_file": "C:\\Users\\Gustavo\\Desktop\\automa\u00e7\u00e3o ifood\\automa-o-apis-delivery\\server\\app.py", "source_location": "L444"}, {"caller_nid": "app_pausar_em_massa", "callee": "append", "source_file": "C:\\Users\\Gustavo\\Desktop\\automa\u00e7\u00e3o ifood\\automa-o-apis-delivery\\server\\app.py", "source_location": "L446"}, {"caller_nid": "app_pausar_em_massa", "callee": "error", "source_file": "C:\\Users\\Gustavo\\Desktop\\automa\u00e7\u00e3o ifood\\automa-o-apis-delivery\\server\\app.py", "source_location": "L448"}, {"caller_nid": "app_pausar_em_massa", "callee": "str", "source_file": "C:\\Users\\Gustavo\\Desktop\\automa\u00e7\u00e3o ifood\\automa-o-apis-delivery\\server\\app.py", "source_location": "L449"}, {"caller_nid": "app_pausar_em_massa", "callee": "append", "source_file": "C:\\Users\\Gustavo\\Desktop\\automa\u00e7\u00e3o ifood\\automa-o-apis-delivery\\server\\app.py", "source_location": "L450"}, {"caller_nid": "app_pausar_em_massa", "callee": "str", "source_file": "C:\\Users\\Gustavo\\Desktop\\automa\u00e7\u00e3o ifood\\automa-o-apis-delivery\\server\\app.py", "source_location": "L450"}, {"caller_nid": "app_pausar_em_massa", "callee": "len", "source_file": "C:\\Users\\Gustavo\\Desktop\\automa\u00e7\u00e3o ifood\\automa-o-apis-delivery\\server\\app.py", "source_location": "L451"}, {"caller_nid": "app_pausar_em_massa", "callee": "sleep", "source_file": "C:\\Users\\Gustavo\\Desktop\\automa\u00e7\u00e3o ifood\\automa-o-apis-delivery\\server\\app.py", "source_location": "L452"}, {"caller_nid": "app_pausar_em_massa", "callee": "sum", "source_file": "C:\\Users\\Gustavo\\Desktop\\automa\u00e7\u00e3o ifood\\automa-o-apis-delivery\\server\\app.py", "source_location": "L454"}, {"caller_nid": "app_pausar_em_massa", "callee": "jsonify", "source_file": "C:\\Users\\Gustavo\\Desktop\\automa\u00e7\u00e3o ifood\\automa-o-apis-delivery\\server\\app.py", "source_location": "L455"}, {"caller_nid": "app_pausar_em_massa", "callee": "len", "source_file": "C:\\Users\\Gustavo\\Desktop\\automa\u00e7\u00e3o ifood\\automa-o-apis-delivery\\server\\app.py", "source_location": "L455"}, {"caller_nid": "app_pausar_em_massa", "callee": "len", "source_file": "C:\\Users\\Gustavo\\Desktop\\automa\u00e7\u00e3o ifood\\automa-o-apis-delivery\\server\\app.py", "source_location": "L455"}, {"caller_nid": "app_get_auditoria", "callee": "min", "source_file": "C:\\Users\\Gustavo\\Desktop\\automa\u00e7\u00e3o ifood\\automa-o-apis-delivery\\server\\app.py", "source_location": "L461"}, {"caller_nid": "app_get_auditoria", "callee": "int", "source_file": "C:\\Users\\Gustavo\\Desktop\\automa\u00e7\u00e3o ifood\\automa-o-apis-delivery\\server\\app.py", "source_location": "L461"}, {"caller_nid": "app_get_auditoria", "callee": "get", "source_file": "C:\\Users\\Gustavo\\Desktop\\automa\u00e7\u00e3o ifood\\automa-o-apis-delivery\\server\\app.py", "source_location": "L461"}, {"caller_nid": "app_get_auditoria", "callee": "jsonify", "source_file": "C:\\Users\\Gustavo\\Desktop\\automa\u00e7\u00e3o ifood\\automa-o-apis-delivery\\server\\app.py", "source_location": "L463"}, {"caller_nid": "app_get_auditoria", "callee": "get", "source_file": "C:\\Users\\Gustavo\\Desktop\\automa\u00e7\u00e3o ifood\\automa-o-apis-delivery\\server\\app.py", "source_location": "L466"}, {"caller_nid": "app_get_auditoria", "callee": "raise_for_status", "source_file": "C:\\Users\\Gustavo\\Desktop\\automa\u00e7\u00e3o ifood\\automa-o-apis-delivery\\server\\app.py", "source_location": "L472"}, {"caller_nid": "app_get_auditoria", "callee": "error", "source_file": "C:\\Users\\Gustavo\\Desktop\\automa\u00e7\u00e3o ifood\\automa-o-apis-delivery\\server\\app.py", "source_location": "L474"}, {"caller_nid": "app_get_auditoria", "callee": "jsonify", "source_file": "C:\\Users\\Gustavo\\Desktop\\automa\u00e7\u00e3o ifood\\automa-o-apis-delivery\\server\\app.py", "source_location": "L475"}, {"caller_nid": "app_get_auditoria", "callee": "get", "source_file": "C:\\Users\\Gustavo\\Desktop\\automa\u00e7\u00e3o ifood\\automa-o-apis-delivery\\server\\app.py", "source_location": "L479"}, {"caller_nid": "app_get_auditoria", "callee": "get", "source_file": "C:\\Users\\Gustavo\\Desktop\\automa\u00e7\u00e3o ifood\\automa-o-apis-delivery\\server\\app.py", "source_location": "L480"}, {"caller_nid": "app_get_auditoria", "callee": "get", "source_file": "C:\\Users\\Gustavo\\Desktop\\automa\u00e7\u00e3o ifood\\automa-o-apis-delivery\\server\\app.py", "source_location": "L481"}, {"caller_nid": "app_get_auditoria", "callee": "get", "source_file": "C:\\Users\\Gustavo\\Desktop\\automa\u00e7\u00e3o ifood\\automa-o-apis-delivery\\server\\app.py", "source_location": "L482"}, {"caller_nid": "app_get_auditoria", "callee": "get", "source_file": "C:\\Users\\Gustavo\\Desktop\\automa\u00e7\u00e3o ifood\\automa-o-apis-delivery\\server\\app.py", "source_location": "L483"}, {"caller_nid": "app_get_auditoria", "callee": "get", "source_file": "C:\\Users\\Gustavo\\Desktop\\automa\u00e7\u00e3o ifood\\automa-o-apis-delivery\\server\\app.py", "source_location": "L484"}, {"caller_nid": "app_get_auditoria", "callee": "get", "source_file": "C:\\Users\\Gustavo\\Desktop\\automa\u00e7\u00e3o ifood\\automa-o-apis-delivery\\server\\app.py", "source_location": "L485"}, {"caller_nid": "app_get_auditoria", "callee": "json", "source_file": "C:\\Users\\Gustavo\\Desktop\\automa\u00e7\u00e3o ifood\\automa-o-apis-delivery\\server\\app.py", "source_location": "L487"}, {"caller_nid": "app_get_auditoria", "callee": "jsonify", "source_file": "C:\\Users\\Gustavo\\Desktop\\automa\u00e7\u00e3o ifood\\automa-o-apis-delivery\\server\\app.py", "source_location": "L489"}, {"caller_nid": "app_listar_usuarios", "callee": "get", "source_file": "C:\\Users\\Gustavo\\Desktop\\automa\u00e7\u00e3o ifood\\automa-o-apis-delivery\\server\\app.py", "source_location": "L495"}, {"caller_nid": "app_listar_usuarios", "callee": "raise_for_status", "source_file": "C:\\Users\\Gustavo\\Desktop\\automa\u00e7\u00e3o ifood\\automa-o-apis-delivery\\server\\app.py", "source_location": "L501"}, {"caller_nid": "app_listar_usuarios", "callee": "jsonify", "source_file": "C:\\Users\\Gustavo\\Desktop\\automa\u00e7\u00e3o ifood\\automa-o-apis-delivery\\server\\app.py", "source_location": "L502"}, {"caller_nid": "app_listar_usuarios", "callee": "json", "source_file": "C:\\Users\\Gustavo\\Desktop\\automa\u00e7\u00e3o ifood\\automa-o-apis-delivery\\server\\app.py", "source_location": "L502"}, {"caller_nid": "app_convidar_usuario", "callee": "get_json", "source_file": "C:\\Users\\Gustavo\\Desktop\\automa\u00e7\u00e3o ifood\\automa-o-apis-delivery\\server\\app.py", "source_location": "L510"}, {"caller_nid": "app_convidar_usuario", "callee": "lower", "source_file": "C:\\Users\\Gustavo\\Desktop\\automa\u00e7\u00e3o ifood\\automa-o-apis-delivery\\server\\app.py", "source_location": "L511"}, {"caller_nid": "app_convidar_usuario", "callee": "strip", "source_file": "C:\\Users\\Gustavo\\Desktop\\automa\u00e7\u00e3o ifood\\automa-o-apis-delivery\\server\\app.py", "source_location": "L511"}, {"caller_nid": "app_convidar_usuario", "callee": "str", "source_file": "C:\\Users\\Gustavo\\Desktop\\automa\u00e7\u00e3o ifood\\automa-o-apis-delivery\\server\\app.py", "source_location": "L511"}, {"caller_nid": "app_convidar_usuario", "callee": "get", "source_file": "C:\\Users\\Gustavo\\Desktop\\automa\u00e7\u00e3o ifood\\automa-o-apis-delivery\\server\\app.py", "source_location": "L511"}, {"caller_nid": "app_convidar_usuario", "callee": "strip", "source_file": "C:\\Users\\Gustavo\\Desktop\\automa\u00e7\u00e3o ifood\\automa-o-apis-delivery\\server\\app.py", "source_location": "L512"}, {"caller_nid": "app_convidar_usuario", "callee": "str", "source_file": "C:\\Users\\Gustavo\\Desktop\\automa\u00e7\u00e3o ifood\\automa-o-apis-delivery\\server\\app.py", "source_location": "L512"}, {"caller_nid": "app_convidar_usuario", "callee": "get", "source_file": "C:\\Users\\Gustavo\\Desktop\\automa\u00e7\u00e3o ifood\\automa-o-apis-delivery\\server\\app.py", "source_location": "L512"}, {"caller_nid": "app_convidar_usuario", "callee": "lower", "source_file": "C:\\Users\\Gustavo\\Desktop\\automa\u00e7\u00e3o ifood\\automa-o-apis-delivery\\server\\app.py", "source_location": "L513"}, {"caller_nid": "app_convidar_usuario", "callee": "strip", "source_file": "C:\\Users\\Gustavo\\Desktop\\automa\u00e7\u00e3o ifood\\automa-o-apis-delivery\\server\\app.py", "source_location": "L513"}, {"caller_nid": "app_convidar_usuario", "callee": "str", "source_file": "C:\\Users\\Gustavo\\Desktop\\automa\u00e7\u00e3o ifood\\automa-o-apis-delivery\\server\\app.py", "source_location": "L513"}, {"caller_nid": "app_convidar_usuario", "callee": "get", "source_file": "C:\\Users\\Gustavo\\Desktop\\automa\u00e7\u00e3o ifood\\automa-o-apis-delivery\\server\\app.py", "source_location": "L513"}, {"caller_nid": "app_convidar_usuario", "callee": "ValueError", "source_file": "C:\\Users\\Gustavo\\Desktop\\automa\u00e7\u00e3o ifood\\automa-o-apis-delivery\\server\\app.py", "source_location": "L516"}, {"caller_nid": "app_convidar_usuario", "callee": "ValueError", "source_file": "C:\\Users\\Gustavo\\Desktop\\automa\u00e7\u00e3o ifood\\automa-o-apis-delivery\\server\\app.py", "source_location": "L518"}, {"caller_nid": "app_convidar_usuario", "callee": "post", "source_file": "C:\\Users\\Gustavo\\Desktop\\automa\u00e7\u00e3o ifood\\automa-o-apis-delivery\\server\\app.py", "source_location": "L520"}, {"caller_nid": "app_convidar_usuario", "callee": "raise_for_status", "source_file": "C:\\Users\\Gustavo\\Desktop\\automa\u00e7\u00e3o ifood\\automa-o-apis-delivery\\server\\app.py", "source_location": "L526"}, {"caller_nid": "app_convidar_usuario", "callee": "jsonify", "source_file": "C:\\Users\\Gustavo\\Desktop\\automa\u00e7\u00e3o ifood\\automa-o-apis-delivery\\server\\app.py", "source_location": "L528"}, {"caller_nid": "app_resetar_senha_usuario", "callee": "join", "source_file": "C:\\Users\\Gustavo\\Desktop\\automa\u00e7\u00e3o ifood\\automa-o-apis-delivery\\server\\app.py", "source_location": "L543"}, {"caller_nid": "app_resetar_senha_usuario", "callee": "choice", "source_file": "C:\\Users\\Gustavo\\Desktop\\automa\u00e7\u00e3o ifood\\automa-o-apis-delivery\\server\\app.py", "source_location": "L543"}, {"caller_nid": "app_resetar_senha_usuario", "callee": "range", "source_file": "C:\\Users\\Gustavo\\Desktop\\automa\u00e7\u00e3o ifood\\automa-o-apis-delivery\\server\\app.py", "source_location": "L543"}, {"caller_nid": "app_resetar_senha_usuario", "callee": "put", "source_file": "C:\\Users\\Gustavo\\Desktop\\automa\u00e7\u00e3o ifood\\automa-o-apis-delivery\\server\\app.py", "source_location": "L545"}, {"caller_nid": "app_resetar_senha_usuario", "callee": "raise_for_status", "source_file": "C:\\Users\\Gustavo\\Desktop\\automa\u00e7\u00e3o ifood\\automa-o-apis-delivery\\server\\app.py", "source_location": "L551"}, {"caller_nid": "app_resetar_senha_usuario", "callee": "jsonify", "source_file": "C:\\Users\\Gustavo\\Desktop\\automa\u00e7\u00e3o ifood\\automa-o-apis-delivery\\server\\app.py", "source_location": "L553"}, {"caller_nid": "app_alterar_papel_usuario", "callee": "get_json", "source_file": "C:\\Users\\Gustavo\\Desktop\\automa\u00e7\u00e3o ifood\\automa-o-apis-delivery\\server\\app.py", "source_location": "L559"}, {"caller_nid": "app_alterar_papel_usuario", "callee": "lower", "source_file": "C:\\Users\\Gustavo\\Desktop\\automa\u00e7\u00e3o ifood\\automa-o-apis-delivery\\server\\app.py", "source_location": "L560"}, {"caller_nid": "app_alterar_papel_usuario", "callee": "strip", "source_file": "C:\\Users\\Gustavo\\Desktop\\automa\u00e7\u00e3o ifood\\automa-o-apis-delivery\\server\\app.py", "source_location": "L560"}, {"caller_nid": "app_alterar_papel_usuario", "callee": "str", "source_file": "C:\\Users\\Gustavo\\Desktop\\automa\u00e7\u00e3o ifood\\automa-o-apis-delivery\\server\\app.py", "source_location": "L560"}, {"caller_nid": "app_alterar_papel_usuario", "callee": "get", "source_file": "C:\\Users\\Gustavo\\Desktop\\automa\u00e7\u00e3o ifood\\automa-o-apis-delivery\\server\\app.py", "source_location": "L560"}, {"caller_nid": "app_alterar_papel_usuario", "callee": "ValueError", "source_file": "C:\\Users\\Gustavo\\Desktop\\automa\u00e7\u00e3o ifood\\automa-o-apis-delivery\\server\\app.py", "source_location": "L562"}, {"caller_nid": "app_alterar_papel_usuario", "callee": "patch", "source_file": "C:\\Users\\Gustavo\\Desktop\\automa\u00e7\u00e3o ifood\\automa-o-apis-delivery\\server\\app.py", "source_location": "L564"}, {"caller_nid": "app_alterar_papel_usuario", "callee": "raise_for_status", "source_file": "C:\\Users\\Gustavo\\Desktop\\automa\u00e7\u00e3o ifood\\automa-o-apis-delivery\\server\\app.py", "source_location": "L571"}, {"caller_nid": "app_alterar_papel_usuario", "callee": "jsonify", "source_file": "C:\\Users\\Gustavo\\Desktop\\automa\u00e7\u00e3o ifood\\automa-o-apis-delivery\\server\\app.py", "source_location": "L573"}]}